{
    "2303693": {
        "AssignmentGrades": {
            "CS101": 75.0,
            "M101": 80.0
        },
        "ExamGrades": {
            "ME101": 75.0
        },
        "ID": "2303693",
        "attendanceRecord": {
            "11/20/2023": "ABSENT"
        },
        "classSchedule": {
            "C001": "Math 2413",
            "C002": "Biology 1302"
        },
        "email": "drcorona@cougarnet.uh.edu",
        "name": "Diego Coronado"
    },
    "2303694": {
        "AssignmentGrades": {
            "CS101": 80.0,
            "M101": 85.0
        },
        "ExamGrades": {
            "SE101": 85.0
        },
        "ID": "2303694",
        "attendanceRecord": {
            "11/20/2023": "ABSENT"
        },
        "classSchedule": {
            "C001": "Math 2413",
            "C002": "Biology 1302"
        },
        "email": "francocm@edu.com",
        "name": "Cassandra Franco"
    },
    "2303695": {
        "AssignmentGrades": {
            "S101": 90.0
        },
        "ExamGrades": {
            "EE101": 90.0
        },
        "ID": "2303695",
        "attendanceRecord": {
            "11/20/2023": "ABSENT"
        },
        "classSchedule": {
            "C001": "Math 2413",
            "C002": "Biology 1302"
        },
        "email": "johnwick@edu.com",
        "name": "John Wick"
    },
    "2303696": {
        "AssignmentGrades": {
            "S101": 88.0
        },
        "ExamGrades": {
            "CSE101": 95.0
        },
        "ID": "2303696",
        "attendanceRecord": {
            "11/20/2023": "ABSENT"
        },
        "classSchedule": {
            "C003": "English 1301"
        },
        "email": "bobfrank@edu.com",
        "name": "Bob Frank"
    },
    "2303697": {
        "AssignmentGrades": {
            "E101": 92.0
        },
        "ExamGrades": {},
        "ID": "2303697",
        "attendanceRecord": {
            "11/20/2023": "ABSENT"
        },
        "classSchedule": {
            "C003": "English 1301",
            "C004": "Computer Science 1301"
        },
        "email": "sallysue@edu.com",
        "name": "Sally Sue"
    },
    "2303698": {
        "AssignmentGrades": {
            "E101": 87.0
        },
        "ExamGrades": {},
        "ID": "2303698",
        "attendanceRecord": {
            "11/20/2023": "ABSENT"
        },
        "classSchedule": {
            "C004": "Computer Science 1301"
        },
        "email": "johndoe@edu.com",
        "name": "John Doe"
    }
}
